README.md
setup.py
motifs/__init__.py
motifs.egg-info/PKG-INFO
motifs.egg-info/SOURCES.txt
motifs.egg-info/dependency_links.txt
motifs.egg-info/requires.txt
motifs.egg-info/top_level.txt