Metadata-Version: 2.1
Name: motifs
Version: 0.1.0
Summary: Network motif management library
Home-page: https://github.com/aplbrain/motifs/tarball/0.1.0
Author: Jordan Matelsky
Author-email: jordan@matelsky.com
License: ISC
Keywords: graph,motif
Platform: UNKNOWN
